odoo9_addon_connector_ecommerce-9.0.1.0.0.99.dev24-py2.7-nspkg.pth
odoo9_addon_connector_ecommerce-9.0.1.0.0.99.dev24.dist-info/METADATA
odoo9_addon_connector_ecommerce-9.0.1.0.0.99.dev24.dist-info/RECORD
odoo9_addon_connector_ecommerce-9.0.1.0.0.99.dev24.dist-info/WHEEL
odoo9_addon_connector_ecommerce-9.0.1.0.0.99.dev24.dist-info/namespace_packages.txt
odoo9_addon_connector_ecommerce-9.0.1.0.0.99.dev24.dist-info/top_level.txt
odoo_addons/connector_ecommerce/README.rst
odoo_addons/connector_ecommerce/__init__.py
odoo_addons/connector_ecommerce/__openerp__.py
odoo_addons/connector_ecommerce/data/ecommerce_data.xml
odoo_addons/connector_ecommerce/i18n/de.po
odoo_addons/connector_ecommerce/i18n/es.po
odoo_addons/connector_ecommerce/i18n/fr.po
odoo_addons/connector_ecommerce/i18n/nl.po
odoo_addons/connector_ecommerce/models/__init__.py
odoo_addons/connector_ecommerce/models/account.py
odoo_addons/connector_ecommerce/models/account_payment_mode.py
odoo_addons/connector_ecommerce/models/event.py
odoo_addons/connector_ecommerce/models/invoice.py
odoo_addons/connector_ecommerce/models/product.py
odoo_addons/connector_ecommerce/models/sale.py
odoo_addons/connector_ecommerce/models/stock.py
odoo_addons/connector_ecommerce/security/ir.model.access.csv
odoo_addons/connector_ecommerce/security/security.xml
odoo_addons/connector_ecommerce/static/description/icon.png
odoo_addons/connector_ecommerce/tests/__init__.py
odoo_addons/connector_ecommerce/tests/test_invoice_event.py
odoo_addons/connector_ecommerce/tests/test_onchange.py
odoo_addons/connector_ecommerce/tests/test_picking_event.py
odoo_addons/connector_ecommerce/unit/__init__.py
odoo_addons/connector_ecommerce/unit/line_builder.py
odoo_addons/connector_ecommerce/unit/sale_order_onchange.py
odoo_addons/connector_ecommerce/views/invoice_view.xml
odoo_addons/connector_ecommerce/views/payment_mode_view.xml
odoo_addons/connector_ecommerce/views/sale_view.xml
odoo_addons/connector_ecommerce/views/stock_view.xml
odoo_addons/connector_ecommerce/wizard/__init__.py
odoo_addons/connector_ecommerce/wizard/sale_ignore_cancel.py
odoo_addons/connector_ecommerce/wizard/sale_ignore_cancel_view.xml
