Metadata-Version: 2.1
Name: odoo9-addon-connector-ecommerce
Version: 9.0.1.0.0.99.dev24
Summary: Connector for E-Commerce
Home-page: http://odoo-connector.com
Author: Camptocamp,Akretion,Odoo Community Association (OCA)
Author-email: support@odoo-community.org
License: AGPL-3
Platform: UNKNOWN
Classifier: Programming Language :: Python
Classifier: Framework :: Odoo
Classifier: License :: OSI Approved :: GNU Affero General Public License v3
Requires-Python: ~=2.7
Requires-Dist: odoo9-addon-connector
Requires-Dist: odoo9-addon-connector-base-product
Requires-Dist: odoo9-addon-sale-automatic-workflow-payment-mode
Requires-Dist: odoo9-addon-sale-exception
Requires-Dist: odoo (<9.1a,>=9.0a)
